spintaxpy/__init__.py
spintaxpy/spintax.py
spintaxpy-1.0.1.dist-info/licenses/LICENSE
spintaxpy-1.0.1.dist-info/METADATA
spintaxpy-1.0.1.dist-info/WHEEL
spintaxpy-1.0.1.dist-info/top_level.txt
spintaxpy-1.0.1.dist-info/RECORD
