Metadata-Version: 2.4
Name: spintaxpy
Version: 1.0.1
Summary: A combinatorial string generation library that creates all possible combinations from templates with variable elements
Home-page: https://github.com/alwahib/spintax-py
Author: alwahib
License-Expression: MIT
Project-URL: Homepage, https://github.com/alwahib/spintax-py
Project-URL: Repository, https://github.com/alwahib/spintax-py
Project-URL: Bug Tracker, https://github.com/alwahib/spintax-py/issues
Keywords: spintax,text generation,combinatorial,string variation,template,pattern
Classifier: Development Status :: 5 - Production/Stable
Classifier: Intended Audience :: Developers
Classifier: Operating System :: OS Independent
Classifier: Programming Language :: Python :: 3
Classifier: Programming Language :: Python :: 3.6
Classifier: Programming Language :: Python :: 3.7
Classifier: Programming Language :: Python :: 3.8
Classifier: Programming Language :: Python :: 3.9
Classifier: Programming Language :: Python :: 3.10
Classifier: Programming Language :: Python :: 3.11
Classifier: Programming Language :: Python :: 3.12
Classifier: Topic :: Software Development :: Libraries :: Python Modules
Classifier: Topic :: Text Processing
Classifier: Topic :: Utilities
Requires-Python: >=3.6
License-File: LICENSE
Dynamic: home-page
Dynamic: license-file
Dynamic: requires-python
